{
    "coding":{
        "title":"Proficient Coder",
        "order":0,
        "organization":{
            "latex":"\\texttt{Python}, \\LaTeX, \\texttt{C++}, \\texttt{Matlab}, \\& \\texttt{R}"
        },
        "duration":"Present",
        "description":[
            ""
        ],
        "highlights":[
            ""
        ],
        "supervisors":[

        ]
    },
    "sos_security":{
        "title":"Office Assistant",
        "order":1,
        "organization":"SOS Security, LLC in Parsippany, NJ",
        "duration":"Summer 2008",
        "description":[
            ""
        ],
        "highlights":[
            ""
        ],
        "supervisors":[
            "jflanagan"
        ]
    },
    "gre_tutor":{
        "title":"Math Tutor",
        "order":2,
        "organization":"Graduate Record Exam (GRE)",
        "duration":"Fall 2008",
        "description":[
            ""
        ],
        "highlights":[
            ""
        ],
        "supervisors":[
            ""
        ]
    },
    "nyc_supreme_court":{
        "title":"Internship",
        "order":3,
        "organization":"Supreme Court of New York",
        "duration":"March 2010",
        "description":[
            ""
        ],
        "highlights":[
            ""
        ],
        "supervisors":[
            "aebelen",
            "ahurkintorres"
        ]
    },
    "radio_license":{
        "title":{
            "latex":"Technician License"
        },
        "order":4,
        "organization":"American Radio Relay League (ARRL)",
        "duration":"July 2010",
        "description":[
            ""
        ],
        "highlights":[
            ""
        ],
        "supervisors":[
            ""
        ]
    },
    "ilr_budget":{
        "title":"Student Employee",
        "order":5,
        "organization":"ILR Budget Office, Cornell University",
        "duration":"Summer 2011",
        "description":[
            ""
        ],
        "highlights":[
            ""
        ],
        "supervisors":[
            "rlmonroe"
        ]
    },
    "leadershape":{
        "title":"Graduate",
        "order":6,
        "organization":
            {
                "latex":"\\textit{The LeaderShape Institute}"
            },
        "duration":"May 2011",
        "description":[
            ""
        ],
        "highlights":[
            ""
        ],
        "supervisors":[
            ""
        ]
    },
    "biosaxs_chess":{
        "title":"Internship",
        "order":7,
        "organization":"Cornell High Energy Sychrotron Source (BioSAXS on F2 and G Beamlines)",
        "duration":"Summer 2013",
        "description":[
            ""
        ],
        "highlights":[
            ""
        ],
        "supervisors":[
            "regillilan",
            "efontes"
        ]
    },
    "mlss":{
        "title":"Graduate",
        "order":8,
        "organization":"Machine Learning Summer School at the University of Texas, Austin",
        "duration":"January 2015",
        "description":[
            ""
        ],
        "highlights":[
            ""
        ],
        "supervisors":[
            ""
        ]
    }
}
